setup.py
egen12312312312312213123123232323.egg-info/PKG-INFO
egen12312312312312213123123232323.egg-info/SOURCES.txt
egen12312312312312213123123232323.egg-info/dependency_links.txt
egen12312312312312213123123232323.egg-info/top_level.txt
new_project/program.py