Metadata-Version: 2.1
Name: egen12312312312312213123123232323
Version: 1.0
Summary: Python BEST PROJECT
Home-page: https://ukr.net
Author: KIRILL
Author-email: egen13@ukr.net
License: UNKNOWN
Platform: UNKNOWN
